{
    "0": {
        "index": "0",
        "year": "2018",
        "month": "January",
        "timeframe": "2018 January",
        "month_code": "1",
        "week": "1",
        "continued_claims": "3133",
        "cont_pct_change_same_wk_last_year": "-26.10%",
        "init_claims": "739",
        "init_pct_change_same_wk_last_year": "-7.00%"
    },
    "1": {
        "index": "1",
        "year": "2018",
        "month": "January",
        "timeframe": "2018 January",
        "month_code": "1",
        "week": "2",
        "continued_claims": "3238",
        "cont_pct_change_same_wk_last_year": "-26.90%",
        "init_claims": "781",
        "init_pct_change_same_wk_last_year": "-0.50%"
    },
    "2": {
        "index": "2",
        "year": "2018",
        "month": "January",
        "timeframe": "2018 January",
        "month_code": "1",
        "week": "3",
        "continued_claims": "3290",
        "cont_pct_change_same_wk_last_year": "-27.60%",
        "init_claims": "539",
        "init_pct_change_same_wk_last_year": "-15.30%"
    },
    "3": {
        "index": "3",
        "year": "2018",
        "month": "January",
        "timeframe": "2018 January",
        "month_code": "1",
        "week": "4",
        "continued_claims": "3323",
        "cont_pct_change_same_wk_last_year": "-28.00%",
        "init_claims": "540",
        "init_pct_change_same_wk_last_year": "-12.30%"
    },
    "4": {
        "index": "4",
        "year": "2018",
        "month": "February",
        "timeframe": "2018 February",
        "month_code": "2",
        "week": "5",
        "continued_claims": "3360",
        "cont_pct_change_same_wk_last_year": "-27.30%",
        "init_claims": "470",
        "init_pct_change_same_wk_last_year": "-14.10%"
    },
    "5": {
        "index": "5",
        "year": "2018",
        "month": "February",
        "timeframe": "2018 February",
        "month_code": "2",
        "week": "6",
        "continued_claims": "3469",
        "cont_pct_change_same_wk_last_year": "-25.60%",
        "init_claims": "500",
        "init_pct_change_same_wk_last_year": "-5.70%"
    },
    "6": {
        "index": "6",
        "year": "2018",
        "month": "February",
        "timeframe": "2018 February",
        "month_code": "2",
        "week": "7",
        "continued_claims": "3545",
        "cont_pct_change_same_wk_last_year": "-23.40%",
        "init_claims": "396",
        "init_pct_change_same_wk_last_year": "-10.00%"
    },
    "7": {
        "index": "7",
        "year": "2018",
        "month": "February",
        "timeframe": "2018 February",
        "month_code": "2",
        "week": "8",
        "continued_claims": "3523",
        "cont_pct_change_same_wk_last_year": "-22.00%",
        "init_claims": "362",
        "init_pct_change_same_wk_last_year": "-13.20%"
    },
    "8": {
        "index": "8",
        "year": "2018",
        "month": "March",
        "timeframe": "2018 March",
        "month_code": "3",
        "week": "9",
        "continued_claims": "3388",
        "cont_pct_change_same_wk_last_year": "-23.50%",
        "init_claims": "399",
        "init_pct_change_same_wk_last_year": "-8.30%"
    },
    "9": {
        "index": "9",
        "year": "2018",
        "month": "March",
        "timeframe": "2018 March",
        "month_code": "3",
        "week": "10",
        "continued_claims": "3233",
        "cont_pct_change_same_wk_last_year": "-25.00%",
        "init_claims": "397",
        "init_pct_change_same_wk_last_year": "-14.30%"
    },
    "10": {
        "index": "10",
        "year": "2018",
        "month": "March",
        "timeframe": "2018 March",
        "month_code": "3",
        "week": "11",
        "continued_claims": "3160",
        "cont_pct_change_same_wk_last_year": "-25.70%",
        "init_claims": "400",
        "init_pct_change_same_wk_last_year": "3.60%"
    },
    "11": {
        "index": "11",
        "year": "2018",
        "month": "March",
        "timeframe": "2018 March",
        "month_code": "3",
        "week": "12",
        "continued_claims": "3057",
        "cont_pct_change_same_wk_last_year": "-26.20%",
        "init_claims": "374",
        "init_pct_change_same_wk_last_year": "-9.70%"
    },
    "12": {
        "index": "12",
        "year": "2018",
        "month": "March",
        "timeframe": "2018 March",
        "month_code": "3",
        "week": "13",
        "continued_claims": "3070",
        "cont_pct_change_same_wk_last_year": "-24.50%",
        "init_claims": "351",
        "init_pct_change_same_wk_last_year": "-16.20%"
    },
    "13": {
        "index": "13",
        "year": "2018",
        "month": "April",
        "timeframe": "2018 April",
        "month_code": "4",
        "week": "14",
        "continued_claims": "3054",
        "cont_pct_change_same_wk_last_year": "-21.90%",
        "init_claims": "483",
        "init_pct_change_same_wk_last_year": "-19.50%"
    },
    "14": {
        "index": "14",
        "year": "2018",
        "month": "April",
        "timeframe": "2018 April",
        "month_code": "4",
        "week": "15",
        "continued_claims": "2941",
        "cont_pct_change_same_wk_last_year": "-21.90%",
        "init_claims": "433",
        "init_pct_change_same_wk_last_year": "-1.10%"
    },
    "15": {
        "index": "15",
        "year": "2018",
        "month": "April",
        "timeframe": "2018 April",
        "month_code": "4",
        "week": "16",
        "continued_claims": "2874",
        "cont_pct_change_same_wk_last_year": "-22.10%",
        "init_claims": "364",
        "init_pct_change_same_wk_last_year": "-18.90%"
    },
    "16": {
        "index": "16",
        "year": "2018",
        "month": "April",
        "timeframe": "2018 April",
        "month_code": "4",
        "week": "17",
        "continued_claims": "2851",
        "cont_pct_change_same_wk_last_year": "-22.40%",
        "init_claims": "325",
        "init_pct_change_same_wk_last_year": "-37.50%"
    },
    "17": {
        "index": "17",
        "year": "2018",
        "month": "May",
        "timeframe": "2018 May",
        "month_code": "5",
        "week": "18",
        "continued_claims": "2692",
        "cont_pct_change_same_wk_last_year": "-27.10%",
        "init_claims": "343",
        "init_pct_change_same_wk_last_year": "-33.30%"
    },
    "18": {
        "index": "18",
        "year": "2018",
        "month": "May",
        "timeframe": "2018 May",
        "month_code": "5",
        "week": "19",
        "continued_claims": "2647",
        "cont_pct_change_same_wk_last_year": "-26.30%",
        "init_claims": "375",
        "init_pct_change_same_wk_last_year": "-25.60%"
    },
    "19": {
        "index": "19",
        "year": "2018",
        "month": "May",
        "timeframe": "2018 May",
        "month_code": "5",
        "week": "20",
        "continued_claims": "2598",
        "cont_pct_change_same_wk_last_year": "-26.40%",
        "init_claims": "366",
        "init_pct_change_same_wk_last_year": "-26.70%"
    },
    "20": {
        "index": "20",
        "year": "2018",
        "month": "May",
        "timeframe": "2018 May",
        "month_code": "5",
        "week": "21",
        "continued_claims": "2556",
        "cont_pct_change_same_wk_last_year": "-23.70%",
        "init_claims": "383",
        "init_pct_change_same_wk_last_year": "-14.30%"
    },
    "21": {
        "index": "21",
        "year": "2018",
        "month": "June",
        "timeframe": "2018 June",
        "month_code": "6",
        "week": "22",
        "continued_claims": "2578",
        "cont_pct_change_same_wk_last_year": "-9.40%",
        "init_claims": "305",
        "init_pct_change_same_wk_last_year": "-20.40%"
    },
    "22": {
        "index": "22",
        "year": "2018",
        "month": "June",
        "timeframe": "2018 June",
        "month_code": "6",
        "week": "23",
        "continued_claims": "2522",
        "cont_pct_change_same_wk_last_year": "-11.10%",
        "init_claims": "436",
        "init_pct_change_same_wk_last_year": "4.60%"
    },
    "23": {
        "index": "23",
        "year": "2018",
        "month": "June",
        "timeframe": "2018 June",
        "month_code": "6",
        "week": "24",
        "continued_claims": "2599",
        "cont_pct_change_same_wk_last_year": "-6.00%",
        "init_claims": "539",
        "init_pct_change_same_wk_last_year": "30.20%"
    },
    "24": {
        "index": "24",
        "year": "2018",
        "month": "June",
        "timeframe": "2018 June",
        "month_code": "6",
        "week": "25",
        "continued_claims": "2695",
        "cont_pct_change_same_wk_last_year": "-0.50%",
        "init_claims": "403",
        "init_pct_change_same_wk_last_year": "3.90%"
    },
    "25": {
        "index": "25",
        "year": "2018",
        "month": "June",
        "timeframe": "2018 June",
        "month_code": "6",
        "week": "26",
        "continued_claims": "2573",
        "cont_pct_change_same_wk_last_year": "-4.20%",
        "init_claims": "340",
        "init_pct_change_same_wk_last_year": "-14.40%"
    },
    "26": {
        "index": "26",
        "year": "2018",
        "month": "July",
        "timeframe": "2018 July",
        "month_code": "7",
        "week": "27",
        "continued_claims": "2622",
        "cont_pct_change_same_wk_last_year": "-5.40%",
        "init_claims": "387",
        "init_pct_change_same_wk_last_year": "-18.70%"
    },
    "27": {
        "index": "27",
        "year": "2018",
        "month": "July",
        "timeframe": "2018 July",
        "month_code": "7",
        "week": "28",
        "continued_claims": "2621",
        "cont_pct_change_same_wk_last_year": "-6.50%",
        "init_claims": "394",
        "init_pct_change_same_wk_last_year": "-18.30%"
    },
    "28": {
        "index": "28",
        "year": "2018",
        "month": "July",
        "timeframe": "2018 July",
        "month_code": "7",
        "week": "29",
        "continued_claims": "2553",
        "cont_pct_change_same_wk_last_year": "-9.80%",
        "init_claims": "336",
        "init_pct_change_same_wk_last_year": "-25.00%"
    },
    "29": {
        "index": "29",
        "year": "2018",
        "month": "July",
        "timeframe": "2018 July",
        "month_code": "7",
        "week": "30",
        "continued_claims": "2540",
        "cont_pct_change_same_wk_last_year": "-7.70%",
        "init_claims": "336",
        "init_pct_change_same_wk_last_year": "-21.70%"
    },
    "30": {
        "index": "30",
        "year": "2018",
        "month": "August",
        "timeframe": "2018 August",
        "month_code": "8",
        "week": "31",
        "continued_claims": "2502",
        "cont_pct_change_same_wk_last_year": "-8.70%",
        "init_claims": "351",
        "init_pct_change_same_wk_last_year": "-20.40%"
    },
    "31": {
        "index": "31",
        "year": "2018",
        "month": "August",
        "timeframe": "2018 August",
        "month_code": "8",
        "week": "32",
        "continued_claims": "2515",
        "cont_pct_change_same_wk_last_year": "-9.10%",
        "init_claims": "352",
        "init_pct_change_same_wk_last_year": "-17.00%"
    },
    "32": {
        "index": "32",
        "year": "2018",
        "month": "August",
        "timeframe": "2018 August",
        "month_code": "8",
        "week": "33",
        "continued_claims": "2378",
        "cont_pct_change_same_wk_last_year": "-13.50%",
        "init_claims": "368",
        "init_pct_change_same_wk_last_year": "-10.90%"
    },
    "33": {
        "index": "33",
        "year": "2018",
        "month": "August",
        "timeframe": "2018 August",
        "month_code": "8",
        "week": "34",
        "continued_claims": "2414",
        "cont_pct_change_same_wk_last_year": "-12.90%",
        "init_claims": "276",
        "init_pct_change_same_wk_last_year": "-33.70%"
    },
    "34": {
        "index": "34",
        "year": "2018",
        "month": "September",
        "timeframe": "2018 September",
        "month_code": "9",
        "week": "35",
        "continued_claims": "2410",
        "cont_pct_change_same_wk_last_year": "-9.00%",
        "init_claims": "359",
        "init_pct_change_same_wk_last_year": "-11.60%"
    },
    "35": {
        "index": "35",
        "year": "2018",
        "month": "September",
        "timeframe": "2018 September",
        "month_code": "9",
        "week": "36",
        "continued_claims": "2385",
        "cont_pct_change_same_wk_last_year": "-10.20%",
        "init_claims": "313",
        "init_pct_change_same_wk_last_year": "-12.60%"
    },
    "36": {
        "index": "36",
        "year": "2018",
        "month": "September",
        "timeframe": "2018 September",
        "month_code": "9",
        "week": "37",
        "continued_claims": "2347",
        "cont_pct_change_same_wk_last_year": "-8.00%",
        "init_claims": "331",
        "init_pct_change_same_wk_last_year": "-6.50%"
    },
    "37": {
        "index": "37",
        "year": "2018",
        "month": "September",
        "timeframe": "2018 September",
        "month_code": "9",
        "week": "38",
        "continued_claims": "2326",
        "cont_pct_change_same_wk_last_year": "-9.60%",
        "init_claims": "342",
        "init_pct_change_same_wk_last_year": "-5.30%"
    },
    "38": {
        "index": "38",
        "year": "2018",
        "month": "September",
        "timeframe": "2018 September",
        "month_code": "9",
        "week": "39",
        "continued_claims": "2322",
        "cont_pct_change_same_wk_last_year": "-9.20%",
        "init_claims": "254",
        "init_pct_change_same_wk_last_year": "-26.40%"
    },
    "39": {
        "index": "39",
        "year": "2018",
        "month": "October",
        "timeframe": "2018 October",
        "month_code": "10",
        "week": "40",
        "continued_claims": "2298",
        "cont_pct_change_same_wk_last_year": "-8.10%",
        "init_claims": "321",
        "init_pct_change_same_wk_last_year": "-26.40%"
    },
    "40": {
        "index": "40",
        "year": "2018",
        "month": "October",
        "timeframe": "2018 October",
        "month_code": "10",
        "week": "41",
        "continued_claims": "2257",
        "cont_pct_change_same_wk_last_year": "-11.80%",
        "init_claims": "394",
        "init_pct_change_same_wk_last_year": "-0.50%"
    },
    "41": {
        "index": "41",
        "year": "2018",
        "month": "October",
        "timeframe": "2018 October",
        "month_code": "10",
        "week": "42",
        "continued_claims": "2242",
        "cont_pct_change_same_wk_last_year": "-12.20%",
        "init_claims": "351",
        "init_pct_change_same_wk_last_year": "-2.50%"
    },
    "42": {
        "index": "42",
        "year": "2018",
        "month": "October",
        "timeframe": "2018 October",
        "month_code": "10",
        "week": "43",
        "continued_claims": "2264",
        "cont_pct_change_same_wk_last_year": "-10.10%",
        "init_claims": "308",
        "init_pct_change_same_wk_last_year": "-22.40%"
    },
    "43": {
        "index": "43",
        "year": "2018",
        "month": "November",
        "timeframe": "2018 November",
        "month_code": "11",
        "week": "44",
        "continued_claims": "2269",
        "cont_pct_change_same_wk_last_year": "-9.90%",
        "init_claims": "303",
        "init_pct_change_same_wk_last_year": "-26.30%"
    },
    "44": {
        "index": "44",
        "year": "2018",
        "month": "November",
        "timeframe": "2018 November",
        "month_code": "11",
        "week": "45",
        "continued_claims": "2286",
        "cont_pct_change_same_wk_last_year": "-10.10%",
        "init_claims": "398",
        "init_pct_change_same_wk_last_year": "-14.40%"
    },
    "45": {
        "index": "45",
        "year": "2018",
        "month": "November",
        "timeframe": "2018 November",
        "month_code": "11",
        "week": "46",
        "continued_claims": "2091",
        "cont_pct_change_same_wk_last_year": "-11.20%",
        "init_claims": "440",
        "init_pct_change_same_wk_last_year": "-7.20%"
    },
    "46": {
        "index": "46",
        "year": "2018",
        "month": "November",
        "timeframe": "2018 November",
        "month_code": "11",
        "week": "47",
        "continued_claims": "2277",
        "cont_pct_change_same_wk_last_year": "-9.10%",
        "init_claims": "291",
        "init_pct_change_same_wk_last_year": "-8.80%"
    },
    "47": {
        "index": "47",
        "year": "2018",
        "month": "December",
        "timeframe": "2018 December",
        "month_code": "12",
        "week": "48",
        "continued_claims": "2239",
        "cont_pct_change_same_wk_last_year": "-12.00%",
        "init_claims": "471",
        "init_pct_change_same_wk_last_year": "3.70%"
    },
    "48": {
        "index": "48",
        "year": "2018",
        "month": "December",
        "timeframe": "2018 December",
        "month_code": "12",
        "week": "49",
        "continued_claims": "2287",
        "cont_pct_change_same_wk_last_year": "-12.50%",
        "init_claims": "443",
        "init_pct_change_same_wk_last_year": "-7.70%"
    },
    "49": {
        "index": "49",
        "year": "2018",
        "month": "December",
        "timeframe": "2018 December",
        "month_code": "12",
        "week": "50",
        "continued_claims": "2442",
        "cont_pct_change_same_wk_last_year": "-11.50%",
        "init_claims": "450",
        "init_pct_change_same_wk_last_year": "-21.60%"
    },
    "50": {
        "index": "50",
        "year": "2018",
        "month": "December",
        "timeframe": "2018 December",
        "month_code": "12",
        "week": "51",
        "continued_claims": "2389",
        "cont_pct_change_same_wk_last_year": "-12.20%",
        "init_claims": "432",
        "init_pct_change_same_wk_last_year": "-21.70%"
    },
    "51": {
        "index": "51",
        "year": "2018",
        "month": "December",
        "timeframe": "2018 December",
        "month_code": "12",
        "week": "52",
        "continued_claims": "2539",
        "cont_pct_change_same_wk_last_year": "-14.70%",
        "init_claims": "405",
        "init_pct_change_same_wk_last_year": "-29.20%"
    },
    "52": {
        "index": "52",
        "year": "2019",
        "month": "January",
        "timeframe": "2019 January",
        "month_code": "1",
        "week": "1",
        "continued_claims": "2653",
        "cont_pct_change_same_wk_last_year": "-15.30%",
        "init_claims": "530",
        "init_pct_change_same_wk_last_year": "-28.30%"
    },
    "53": {
        "index": "53",
        "year": "2019",
        "month": "January",
        "timeframe": "2019 January",
        "month_code": "1",
        "week": "2",
        "continued_claims": "2703",
        "cont_pct_change_same_wk_last_year": "-16.50%",
        "init_claims": "751",
        "init_pct_change_same_wk_last_year": "-3.80%"
    },
    "54": {
        "index": "54",
        "year": "2019",
        "month": "January",
        "timeframe": "2019 January",
        "month_code": "1",
        "week": "3",
        "continued_claims": "2902",
        "cont_pct_change_same_wk_last_year": "-11.80%",
        "init_claims": "632",
        "init_pct_change_same_wk_last_year": "17.30%"
    },
    "55": {
        "index": "55",
        "year": "2019",
        "month": "January",
        "timeframe": "2019 January",
        "month_code": "1",
        "week": "4",
        "continued_claims": "3006",
        "cont_pct_change_same_wk_last_year": "-9.50%",
        "init_claims": "474",
        "init_pct_change_same_wk_last_year": "-12.20%"
    },
    "56": {
        "index": "56",
        "year": "2019",
        "month": "February",
        "timeframe": "2019 February",
        "month_code": "2",
        "week": "5",
        "continued_claims": "3043",
        "cont_pct_change_same_wk_last_year": "-9.40%",
        "init_claims": "522",
        "init_pct_change_same_wk_last_year": "11.10%"
    },
    "57": {
        "index": "57",
        "year": "2019",
        "month": "February",
        "timeframe": "2019 February",
        "month_code": "2",
        "week": "6",
        "continued_claims": "3074",
        "cont_pct_change_same_wk_last_year": "-11.40%",
        "init_claims": "453",
        "init_pct_change_same_wk_last_year": "-9.40%"
    },
    "58": {
        "index": "58",
        "year": "2019",
        "month": "February",
        "timeframe": "2019 February",
        "month_code": "2",
        "week": "7",
        "continued_claims": "3076",
        "cont_pct_change_same_wk_last_year": "-13.20%",
        "init_claims": "419",
        "init_pct_change_same_wk_last_year": "5.80%"
    },
    "59": {
        "index": "59",
        "year": "2019",
        "month": "February",
        "timeframe": "2019 February",
        "month_code": "2",
        "week": "8",
        "continued_claims": "2962",
        "cont_pct_change_same_wk_last_year": "-15.90%",
        "init_claims": "383",
        "init_pct_change_same_wk_last_year": "5.80%"
    },
    "60": {
        "index": "60",
        "year": "2019",
        "month": "March",
        "timeframe": "2019 March",
        "month_code": "3",
        "week": "9",
        "continued_claims": "2926",
        "cont_pct_change_same_wk_last_year": "-13.60%",
        "init_claims": "310",
        "init_pct_change_same_wk_last_year": "-22.30%"
    },
    "61": {
        "index": "61",
        "year": "2019",
        "month": "March",
        "timeframe": "2019 March",
        "month_code": "3",
        "week": "10",
        "continued_claims": "2904",
        "cont_pct_change_same_wk_last_year": "-10.20%",
        "init_claims": "350",
        "init_pct_change_same_wk_last_year": "-11.80%"
    },
    "62": {
        "index": "62",
        "year": "2019",
        "month": "March",
        "timeframe": "2019 March",
        "month_code": "3",
        "week": "11",
        "continued_claims": "2777",
        "cont_pct_change_same_wk_last_year": "-12.10%",
        "init_claims": "304",
        "init_pct_change_same_wk_last_year": "-24.00%"
    },
    "63": {
        "index": "63",
        "year": "2019",
        "month": "March",
        "timeframe": "2019 March",
        "month_code": "3",
        "week": "12",
        "continued_claims": "2705",
        "cont_pct_change_same_wk_last_year": "-11.50%",
        "init_claims": "300",
        "init_pct_change_same_wk_last_year": "-19.80%"
    },
    "64": {
        "index": "64",
        "year": "2019",
        "month": "March",
        "timeframe": "2019 March",
        "month_code": "3",
        "week": "13",
        "continued_claims": "2646",
        "cont_pct_change_same_wk_last_year": "-13.80%",
        "init_claims": "260",
        "init_pct_change_same_wk_last_year": "-25.90%"
    },
    "65": {
        "index": "65",
        "year": "2019",
        "month": "April",
        "timeframe": "2019 April",
        "month_code": "4",
        "week": "14",
        "continued_claims": "2438",
        "cont_pct_change_same_wk_last_year": "-20.20%",
        "init_claims": "353",
        "init_pct_change_same_wk_last_year": "-26.90%"
    },
    "66": {
        "index": "66",
        "year": "2019",
        "month": "April",
        "timeframe": "2019 April",
        "month_code": "4",
        "week": "15",
        "continued_claims": "2397",
        "cont_pct_change_same_wk_last_year": "-18.50%",
        "init_claims": "355",
        "init_pct_change_same_wk_last_year": "-18.00%"
    },
    "67": {
        "index": "67",
        "year": "2019",
        "month": "April",
        "timeframe": "2019 April",
        "month_code": "4",
        "week": "16",
        "continued_claims": "2328",
        "cont_pct_change_same_wk_last_year": "-19.00%",
        "init_claims": "322",
        "init_pct_change_same_wk_last_year": "-11.50%"
    },
    "68": {
        "index": "68",
        "year": "2019",
        "month": "April",
        "timeframe": "2019 April",
        "month_code": "4",
        "week": "17",
        "continued_claims": "2287",
        "cont_pct_change_same_wk_last_year": "-19.80%",
        "init_claims": "336",
        "init_pct_change_same_wk_last_year": "3.40%"
    },
    "69": {
        "index": "69",
        "year": "2019",
        "month": "May",
        "timeframe": "2019 May",
        "month_code": "5",
        "week": "18",
        "continued_claims": "2275",
        "cont_pct_change_same_wk_last_year": "-15.50%",
        "init_claims": "343",
        "init_pct_change_same_wk_last_year": "0.00%"
    },
    "70": {
        "index": "70",
        "year": "2019",
        "month": "May",
        "timeframe": "2019 May",
        "month_code": "5",
        "week": "19",
        "continued_claims": "2244",
        "cont_pct_change_same_wk_last_year": "-15.20%",
        "init_claims": "305",
        "init_pct_change_same_wk_last_year": "-18.70%"
    },
    "71": {
        "index": "71",
        "year": "2019",
        "month": "May",
        "timeframe": "2019 May",
        "month_code": "5",
        "week": "20",
        "continued_claims": "2276",
        "cont_pct_change_same_wk_last_year": "-12.40%",
        "init_claims": "325",
        "init_pct_change_same_wk_last_year": "-11.20%"
    },
    "72": {
        "index": "72",
        "year": "2019",
        "month": "May",
        "timeframe": "2019 May",
        "month_code": "5",
        "week": "21",
        "continued_claims": "2241",
        "cont_pct_change_same_wk_last_year": "-12.30%",
        "init_claims": "295",
        "init_pct_change_same_wk_last_year": "-23.00%"
    },
    "73": {
        "index": "73",
        "year": "2019",
        "month": "June",
        "timeframe": "2019 June",
        "month_code": "6",
        "week": "22",
        "continued_claims": "2187",
        "cont_pct_change_same_wk_last_year": "-15.20%",
        "init_claims": "324",
        "init_pct_change_same_wk_last_year": "6.20%"
    },
    "74": {
        "index": "74",
        "year": "2019",
        "month": "June",
        "timeframe": "2019 June",
        "month_code": "6",
        "week": "23",
        "continued_claims": "2211",
        "cont_pct_change_same_wk_last_year": "-12.30%",
        "init_claims": "365",
        "init_pct_change_same_wk_last_year": "-16.30%"
    },
    "75": {
        "index": "75",
        "year": "2019",
        "month": "June",
        "timeframe": "2019 June",
        "month_code": "6",
        "week": "24",
        "continued_claims": "2238",
        "cont_pct_change_same_wk_last_year": "-13.90%",
        "init_claims": "338",
        "init_pct_change_same_wk_last_year": "-37.30%"
    },
    "76": {
        "index": "76",
        "year": "2019",
        "month": "June",
        "timeframe": "2019 June",
        "month_code": "6",
        "week": "25",
        "continued_claims": "2162",
        "cont_pct_change_same_wk_last_year": "-19.80%",
        "init_claims": "347",
        "init_pct_change_same_wk_last_year": "-13.90%"
    },
    "77": {
        "index": "77",
        "year": "2019",
        "month": "June",
        "timeframe": "2019 June",
        "month_code": "6",
        "week": "26",
        "continued_claims": "2065",
        "cont_pct_change_same_wk_last_year": "-19.70%",
        "init_claims": "329",
        "init_pct_change_same_wk_last_year": "-3.20%"
    },
    "78": {
        "index": "78",
        "year": "2019",
        "month": "July",
        "timeframe": "2019 July",
        "month_code": "7",
        "week": "27",
        "continued_claims": "2248",
        "cont_pct_change_same_wk_last_year": "-14.30%",
        "init_claims": "285",
        "init_pct_change_same_wk_last_year": "-26.40%"
    },
    "79": {
        "index": "79",
        "year": "2019",
        "month": "July",
        "timeframe": "2019 July",
        "month_code": "7",
        "week": "28",
        "continued_claims": "2252",
        "cont_pct_change_same_wk_last_year": "-14.10%",
        "init_claims": "421",
        "init_pct_change_same_wk_last_year": "6.90%"
    },
    "80": {
        "index": "80",
        "year": "2019",
        "month": "July",
        "timeframe": "2019 July",
        "month_code": "7",
        "week": "29",
        "continued_claims": "2253",
        "cont_pct_change_same_wk_last_year": "-11.80%",
        "init_claims": "327",
        "init_pct_change_same_wk_last_year": "-2.70%"
    },
    "81": {
        "index": "81",
        "year": "2019",
        "month": "July",
        "timeframe": "2019 July",
        "month_code": "7",
        "week": "30",
        "continued_claims": "2254",
        "cont_pct_change_same_wk_last_year": "-11.30%",
        "init_claims": "304",
        "init_pct_change_same_wk_last_year": "-9.50%"
    },
    "82": {
        "index": "82",
        "year": "2019",
        "month": "August",
        "timeframe": "2019 August",
        "month_code": "8",
        "week": "31",
        "continued_claims": "2282",
        "cont_pct_change_same_wk_last_year": "-8.80%",
        "init_claims": "337",
        "init_pct_change_same_wk_last_year": "-4.00%"
    },
    "83": {
        "index": "83",
        "year": "2019",
        "month": "August",
        "timeframe": "2019 August",
        "month_code": "8",
        "week": "32",
        "continued_claims": "2235",
        "cont_pct_change_same_wk_last_year": "-11.10%",
        "init_claims": "349",
        "init_pct_change_same_wk_last_year": "-0.90%"
    },
    "84": {
        "index": "84",
        "year": "2019",
        "month": "August",
        "timeframe": "2019 August",
        "month_code": "8",
        "week": "33",
        "continued_claims": "2239",
        "cont_pct_change_same_wk_last_year": "-5.80%",
        "init_claims": "300",
        "init_pct_change_same_wk_last_year": "-18.50%"
    },
    "85": {
        "index": "85",
        "year": "2019",
        "month": "August",
        "timeframe": "2019 August",
        "month_code": "8",
        "week": "34",
        "continued_claims": "2245",
        "cont_pct_change_same_wk_last_year": "-7.00%",
        "init_claims": "289",
        "init_pct_change_same_wk_last_year": "4.70%"
    },
    "86": {
        "index": "86",
        "year": "2019",
        "month": "August",
        "timeframe": "2019 August",
        "month_code": "8",
        "week": "35",
        "continued_claims": "2142",
        "cont_pct_change_same_wk_last_year": "-11.10%",
        "init_claims": "290",
        "init_pct_change_same_wk_last_year": "-19.20%"
    },
    "87": {
        "index": "87",
        "year": "2019",
        "month": "September",
        "timeframe": "2019 September",
        "month_code": "9",
        "week": "36",
        "continued_claims": "2152",
        "cont_pct_change_same_wk_last_year": "-9.80%",
        "init_claims": "291",
        "init_pct_change_same_wk_last_year": "-7.00%"
    },
    "88": {
        "index": "88",
        "year": "2019",
        "month": "September",
        "timeframe": "2019 September",
        "month_code": "9",
        "week": "37",
        "continued_claims": "2162",
        "cont_pct_change_same_wk_last_year": "-7.90%",
        "init_claims": "325",
        "init_pct_change_same_wk_last_year": "-1.80%"
    },
    "89": {
        "index": "89",
        "year": "2019",
        "month": "September",
        "timeframe": "2019 September",
        "month_code": "9",
        "week": "38",
        "continued_claims": "2159",
        "cont_pct_change_same_wk_last_year": "-7.20%",
        "init_claims": "346",
        "init_pct_change_same_wk_last_year": "1.20%"
    },
    "90": {
        "index": "90",
        "year": "2019",
        "month": "September",
        "timeframe": "2019 September",
        "month_code": "9",
        "week": "39",
        "continued_claims": "2138",
        "cont_pct_change_same_wk_last_year": "-7.90%",
        "init_claims": "281",
        "init_pct_change_same_wk_last_year": "10.60%"
    },
    "91": {
        "index": "91",
        "year": "2019",
        "month": "October",
        "timeframe": "2019 October",
        "month_code": "10",
        "week": "40",
        "continued_claims": "2148",
        "cont_pct_change_same_wk_last_year": "-6.50%",
        "init_claims": "341",
        "init_pct_change_same_wk_last_year": "6.20%"
    },
    "92": {
        "index": "92",
        "year": "2019",
        "month": "October",
        "timeframe": "2019 October",
        "month_code": "10",
        "week": "41",
        "continued_claims": "2095",
        "cont_pct_change_same_wk_last_year": "-7.20%",
        "init_claims": "394",
        "init_pct_change_same_wk_last_year": "0.00%"
    },
    "93": {
        "index": "93",
        "year": "2019",
        "month": "October",
        "timeframe": "2019 October",
        "month_code": "10",
        "week": "42",
        "continued_claims": "2161",
        "cont_pct_change_same_wk_last_year": "-3.60%",
        "init_claims": "378",
        "init_pct_change_same_wk_last_year": "7.70%"
    },
    "94": {
        "index": "94",
        "year": "2019",
        "month": "October",
        "timeframe": "2019 October",
        "month_code": "10",
        "week": "43",
        "continued_claims": "2125",
        "cont_pct_change_same_wk_last_year": "-6.10%",
        "init_claims": "318",
        "init_pct_change_same_wk_last_year": "3.20%"
    },
    "95": {
        "index": "95",
        "year": "2019",
        "month": "November",
        "timeframe": "2019 November",
        "month_code": "11",
        "week": "44",
        "continued_claims": "2109",
        "cont_pct_change_same_wk_last_year": "-7.10%",
        "init_claims": "319",
        "init_pct_change_same_wk_last_year": "5.30%"
    },
    "96": {
        "index": "96",
        "year": "2019",
        "month": "November",
        "timeframe": "2019 November",
        "month_code": "11",
        "week": "45",
        "continued_claims": "2114",
        "cont_pct_change_same_wk_last_year": "-7.50%",
        "init_claims": "384",
        "init_pct_change_same_wk_last_year": "-3.50%"
    },
    "97": {
        "index": "97",
        "year": "2019",
        "month": "November",
        "timeframe": "2019 November",
        "month_code": "11",
        "week": "46",
        "continued_claims": "2148",
        "cont_pct_change_same_wk_last_year": "2.70%",
        "init_claims": "367",
        "init_pct_change_same_wk_last_year": "-16.60%"
    },
    "98": {
        "index": "98",
        "year": "2019",
        "month": "November",
        "timeframe": "2019 November",
        "month_code": "11",
        "week": "47",
        "continued_claims": "2073",
        "cont_pct_change_same_wk_last_year": "-9.00%",
        "init_claims": "399",
        "init_pct_change_same_wk_last_year": "37.10%"
    },
    "99": {
        "index": "99",
        "year": "2019",
        "month": "November",
        "timeframe": "2019 November",
        "month_code": "11",
        "week": "48",
        "continued_claims": "2148",
        "cont_pct_change_same_wk_last_year": "-4.10%",
        "init_claims": "244",
        "init_pct_change_same_wk_last_year": "-48.20%"
    },
    "100": {
        "index": "100",
        "year": "2019",
        "month": "December",
        "timeframe": "2019 December",
        "month_code": "12",
        "week": "49",
        "continued_claims": "2182",
        "cont_pct_change_same_wk_last_year": "-4.60%",
        "init_claims": "417",
        "init_pct_change_same_wk_last_year": "-5.90%"
    },
    "101": {
        "index": "101",
        "year": "2019",
        "month": "December",
        "timeframe": "2019 December",
        "month_code": "12",
        "week": "50",
        "continued_claims": "2399",
        "cont_pct_change_same_wk_last_year": "-1.80%",
        "init_claims": "567",
        "init_pct_change_same_wk_last_year": "26.00%"
    },
    "102": {
        "index": "102",
        "year": "2019",
        "month": "December",
        "timeframe": "2019 December",
        "month_code": "12",
        "week": "51",
        "continued_claims": "2501",
        "cont_pct_change_same_wk_last_year": "4.70%",
        "init_claims": "481",
        "init_pct_change_same_wk_last_year": "11.30%"
    },
    "103": {
        "index": "103",
        "year": "2019",
        "month": "December",
        "timeframe": "2019 December",
        "month_code": "12",
        "week": "52",
        "continued_claims": "2733",
        "cont_pct_change_same_wk_last_year": "7.60%",
        "init_claims": "371",
        "init_pct_change_same_wk_last_year": "-8.40%"
    },
    "104": {
        "index": "104",
        "year": "2020",
        "month": "January",
        "timeframe": "2020 January",
        "month_code": "1",
        "week": "1",
        "continued_claims": "2839",
        "cont_pct_change_same_wk_last_year": "7.00%",
        "init_claims": "453",
        "init_pct_change_same_wk_last_year": "-14.50%"
    },
    "105": {
        "index": "105",
        "year": "2020",
        "month": "January",
        "timeframe": "2020 January",
        "month_code": "1",
        "week": "2",
        "continued_claims": "2880",
        "cont_pct_change_same_wk_last_year": "6.50%",
        "init_claims": "591",
        "init_pct_change_same_wk_last_year": "-21.30%"
    },
    "106": {
        "index": "106",
        "year": "2020",
        "month": "January",
        "timeframe": "2020 January",
        "month_code": "1",
        "week": "3",
        "continued_claims": "2925",
        "cont_pct_change_same_wk_last_year": "0.80%",
        "init_claims": "468",
        "init_pct_change_same_wk_last_year": "-25.90%"
    },
    "107": {
        "index": "107",
        "year": "2020",
        "month": "January",
        "timeframe": "2020 January",
        "month_code": "1",
        "week": "4",
        "continued_claims": "2937",
        "cont_pct_change_same_wk_last_year": "-2.30%",
        "init_claims": "420",
        "init_pct_change_same_wk_last_year": "-11.40%"
    },
    "108": {
        "index": "108",
        "year": "2020",
        "month": "February",
        "timeframe": "2020 February",
        "month_code": "2",
        "week": "5",
        "continued_claims": "3064",
        "cont_pct_change_same_wk_last_year": "0.70%",
        "init_claims": "416",
        "init_pct_change_same_wk_last_year": "-20.30%"
    },
    "109": {
        "index": "109",
        "year": "2020",
        "month": "February",
        "timeframe": "2020 February",
        "month_code": "2",
        "week": "6",
        "continued_claims": "3077",
        "cont_pct_change_same_wk_last_year": "0.10%",
        "init_claims": "410",
        "init_pct_change_same_wk_last_year": "-9.50%"
    },
    "110": {
        "index": "110",
        "year": "2020",
        "month": "February",
        "timeframe": "2020 February",
        "month_code": "2",
        "week": "7",
        "continued_claims": "3129",
        "cont_pct_change_same_wk_last_year": "1.70%",
        "init_claims": "382",
        "init_pct_change_same_wk_last_year": "-8.80%"
    },
    "111": {
        "index": "111",
        "year": "2020",
        "month": "February",
        "timeframe": "2020 February",
        "month_code": "2",
        "week": "8",
        "continued_claims": "3012",
        "cont_pct_change_same_wk_last_year": "1.70%",
        "init_claims": "348",
        "init_pct_change_same_wk_last_year": "-9.10%"
    },
    "112": {
        "index": "112",
        "year": "2020",
        "month": "February",
        "timeframe": "2020 February",
        "month_code": "2",
        "week": "9",
        "continued_claims": "2976",
        "cont_pct_change_same_wk_last_year": "1.70%",
        "init_claims": "324",
        "init_pct_change_same_wk_last_year": "4.50%"
    },
    "113": {
        "index": "113",
        "year": "2020",
        "month": "March",
        "timeframe": "2020 March",
        "month_code": "3",
        "week": "10",
        "continued_claims": "2935",
        "cont_pct_change_same_wk_last_year": "1.10%",
        "init_claims": "298",
        "init_pct_change_same_wk_last_year": "-14.90%"
    },
    "114": {
        "index": "114",
        "year": "2020",
        "month": "March",
        "timeframe": "2020 March",
        "month_code": "3",
        "week": "11",
        "continued_claims": "3028",
        "cont_pct_change_same_wk_last_year": "9.00%",
        "init_claims": "425",
        "init_pct_change_same_wk_last_year": "39.80%"
    },
    "115": {
        "index": "115",
        "year": "2020",
        "month": "March",
        "timeframe": "2020 March",
        "month_code": "3",
        "week": "12",
        "continued_claims": "4736",
        "cont_pct_change_same_wk_last_year": "75.10%",
        "init_claims": "10173",
        "init_pct_change_same_wk_last_year": "3291.00%"
    },
    "116": {
        "index": "116",
        "year": "2020",
        "month": "March",
        "timeframe": "2020 March",
        "month_code": "3",
        "week": "13",
        "continued_claims": "10682",
        "cont_pct_change_same_wk_last_year": "303.70%",
        "init_claims": "13546",
        "init_pct_change_same_wk_last_year": "5110.00%"
    },
    "117": {
        "index": "117",
        "year": "2020",
        "month": "April",
        "timeframe": "2020 April",
        "month_code": "4",
        "week": "14",
        "continued_claims": "18189",
        "cont_pct_change_same_wk_last_year": "646.10%",
        "init_claims": "13603",
        "init_pct_change_same_wk_last_year": "3753.50%"
    },
    "118": {
        "index": "118",
        "year": "2020",
        "month": "April",
        "timeframe": "2020 April",
        "month_code": "4",
        "week": "15",
        "continued_claims": "24549",
        "cont_pct_change_same_wk_last_year": "924.20%",
        "init_claims": "15285",
        "init_pct_change_same_wk_last_year": "4205.60%"
    },
    "119": {
        "index": "119",
        "year": "2020",
        "month": "April",
        "timeframe": "2020 April",
        "month_code": "4",
        "week": "16",
        "continued_claims": "30447",
        "cont_pct_change_same_wk_last_year": "1207.90%",
        "init_claims": "10510",
        "init_pct_change_same_wk_last_year": "3164.00%"
    },
    "120": {
        "index": "120",
        "year": "2020",
        "month": "April",
        "timeframe": "2020 April",
        "month_code": "4",
        "week": "17",
        "continued_claims": "32977",
        "cont_pct_change_same_wk_last_year": "1341.90%",
        "init_claims": "8493",
        "init_pct_change_same_wk_last_year": "2427.70%"
    },
    "121": {
        "index": "121",
        "year": "2020",
        "month": "May",
        "timeframe": "2020 May",
        "month_code": "5",
        "week": "18",
        "continued_claims": "34755",
        "cont_pct_change_same_wk_last_year": "1427.70%",
        "init_claims": "7596",
        "init_pct_change_same_wk_last_year": "2114.60%"
    },
    "122": {
        "index": "122",
        "year": "2020",
        "month": "May",
        "timeframe": "2020 May",
        "month_code": "5",
        "week": "19",
        "continued_claims": "35607",
        "cont_pct_change_same_wk_last_year": "1486.80%",
        "init_claims": "5377",
        "init_pct_change_same_wk_last_year": "1663.00%"
    },
    "123": {
        "index": "123",
        "year": "2020",
        "month": "May",
        "timeframe": "2020 May",
        "month_code": "5",
        "week": "20",
        "continued_claims": "36019",
        "cont_pct_change_same_wk_last_year": "1482.60%",
        "init_claims": "5844",
        "init_pct_change_same_wk_last_year": "1698.20%"
    },
    "124": {
        "index": "124",
        "year": "2020",
        "month": "May",
        "timeframe": "2020 May",
        "month_code": "5",
        "week": "21",
        "continued_claims": "35714",
        "cont_pct_change_same_wk_last_year": "1493.70%",
        "init_claims": "5240",
        "init_pct_change_same_wk_last_year": "1676.30%"
    },
    "125": {
        "index": "125",
        "year": "2020",
        "month": "May",
        "timeframe": "2020 May",
        "month_code": "5",
        "week": "22",
        "continued_claims": "35355",
        "cont_pct_change_same_wk_last_year": "1516.60%",
        "init_claims": "4572",
        "init_pct_change_same_wk_last_year": "1311.10%"
    },
    "126": {
        "index": "126",
        "year": "2020",
        "month": "June",
        "timeframe": "2020 June",
        "month_code": "6",
        "week": "23",
        "continued_claims": "35474",
        "cont_pct_change_same_wk_last_year": "1504.40%",
        "init_claims": "4650",
        "init_pct_change_same_wk_last_year": "1174.00%"
    },
    "127": {
        "index": "127",
        "year": "2020",
        "month": "June",
        "timeframe": "2020 June",
        "month_code": "6",
        "week": "24",
        "continued_claims": "35425",
        "cont_pct_change_same_wk_last_year": "1482.90%",
        "init_claims": "5308",
        "init_pct_change_same_wk_last_year": "1470.40%"
    },
    "128": {
        "index": "128",
        "year": "2020",
        "month": "June",
        "timeframe": "2020 June",
        "month_code": "6",
        "week": "25",
        "continued_claims": "34908",
        "cont_pct_change_same_wk_last_year": "1514.60%",
        "init_claims": "6507",
        "init_pct_change_same_wk_last_year": "1775.20%"
    },
    "129": {
        "index": "129",
        "year": "2020",
        "month": "June",
        "timeframe": "2020 June",
        "month_code": "6",
        "week": "26",
        "continued_claims": "34957",
        "cont_pct_change_same_wk_last_year": "1592.80%",
        "init_claims": "11115",
        "init_pct_change_same_wk_last_year": "3278.40%"
    },
    "130": {
        "index": "130",
        "year": "2020",
        "month": "July",
        "timeframe": "2020 July",
        "month_code": "7",
        "week": "27",
        "continued_claims": "35028",
        "cont_pct_change_same_wk_last_year": "1458.20%",
        "init_claims": "4633",
        "init_pct_change_same_wk_last_year": "1525.60%"
    },
    "131": {
        "index": "131",
        "year": "2020",
        "month": "July",
        "timeframe": "2020 July",
        "month_code": "7",
        "week": "28",
        "continued_claims": "36651",
        "cont_pct_change_same_wk_last_year": "1527.50%",
        "init_claims": "0",
        "init_pct_change_same_wk_last_year": ""
    },
    "132": {
        "index": "132",
        "year": "2020",
        "month": "July",
        "timeframe": "2020 July",
        "month_code": "7",
        "week": "29",
        "continued_claims": "35561",
        "cont_pct_change_same_wk_last_year": "1478.40%",
        "init_claims": "5322",
        "init_pct_change_same_wk_last_year": "1527.50%"
    },
    "133": {
        "index": "133",
        "year": "2020",
        "month": "July",
        "timeframe": "2020 July",
        "month_code": "7",
        "week": "30",
        "continued_claims": "35156",
        "cont_pct_change_same_wk_last_year": "1459.70%",
        "init_claims": "6338",
        "init_pct_change_same_wk_last_year": "1984.90%"
    },
    "134": {
        "index": "134",
        "year": "2020",
        "month": "August",
        "timeframe": "2020 August",
        "month_code": "8",
        "week": "31",
        "continued_claims": "32086",
        "cont_pct_change_same_wk_last_year": "1306.00%",
        "init_claims": "2925",
        "init_pct_change_same_wk_last_year": "768.00%"
    },
    "135": {
        "index": "135",
        "year": "2020",
        "month": "August",
        "timeframe": "2020 August",
        "month_code": "8",
        "week": "32",
        "continued_claims": "30353",
        "cont_pct_change_same_wk_last_year": "1258.10%",
        "init_claims": "2193",
        "init_pct_change_same_wk_last_year": "528.40%"
    },
    "136": {
        "index": "136",
        "year": "2020",
        "month": "August",
        "timeframe": "2020 August",
        "month_code": "8",
        "week": "33",
        "continued_claims": "29627",
        "cont_pct_change_same_wk_last_year": "1223.20%",
        "init_claims": "2741",
        "init_pct_change_same_wk_last_year": "813.70%"
    },
    "137": {
        "index": "137",
        "year": "2020",
        "month": "August",
        "timeframe": "2020 August",
        "month_code": "8",
        "week": "34",
        "continued_claims": "28737",
        "cont_pct_change_same_wk_last_year": "1180.00%",
        "init_claims": "2276",
        "init_pct_change_same_wk_last_year": "687.50%"
    },
    "138": {
        "index": "138",
        "year": "2020",
        "month": "August",
        "timeframe": "2020 August",
        "month_code": "8",
        "week": "35",
        "continued_claims": "28003",
        "cont_pct_change_same_wk_last_year": "1207.30%",
        "init_claims": "2177",
        "init_pct_change_same_wk_last_year": "650.70%"
    },
    "139": {
        "index": "139",
        "year": "2020",
        "month": "September",
        "timeframe": "2020 September",
        "month_code": "9",
        "week": "36",
        "continued_claims": "27608",
        "cont_pct_change_same_wk_last_year": "1182.90%",
        "init_claims": "2515",
        "init_pct_change_same_wk_last_year": "764.30%"
    },
    "140": {
        "index": "140",
        "year": "2020",
        "month": "September",
        "timeframe": "2020 September",
        "month_code": "9",
        "week": "37",
        "continued_claims": "26944",
        "cont_pct_change_same_wk_last_year": "1146.30%",
        "init_claims": "2899",
        "init_pct_change_same_wk_last_year": "792.00%"
    },
    "141": {
        "index": "141",
        "year": "2020",
        "month": "September",
        "timeframe": "2020 September",
        "month_code": "9",
        "week": "38",
        "continued_claims": "25311",
        "cont_pct_change_same_wk_last_year": "1072.30%",
        "init_claims": "3080",
        "init_pct_change_same_wk_last_year": "790.20%"
    },
    "142": {
        "index": "142",
        "year": "2020",
        "month": "September",
        "timeframe": "2020 September",
        "month_code": "9",
        "week": "39",
        "continued_claims": "22612",
        "cont_pct_change_same_wk_last_year": "957.60%",
        "init_claims": "2494",
        "init_pct_change_same_wk_last_year": "787.50%"
    },
    "143": {
        "index": "143",
        "year": "2020",
        "month": "October",
        "timeframe": "2020 October",
        "month_code": "10",
        "week": "40",
        "continued_claims": "20010",
        "cont_pct_change_same_wk_last_year": "831.60%",
        "init_claims": "2277",
        "init_pct_change_same_wk_last_year": "567.70%"
    },
    "144": {
        "index": "144",
        "year": "2020",
        "month": "October",
        "timeframe": "2020 October",
        "month_code": "10",
        "week": "41",
        "continued_claims": "18131",
        "cont_pct_change_same_wk_last_year": "765.40%",
        "init_claims": "17133",
        "init_pct_change_same_wk_last_year": "4248.50%"
    },
    "145": {
        "index": "145",
        "year": "2020",
        "month": "October",
        "timeframe": "2020 October",
        "month_code": "10",
        "week": "42",
        "continued_claims": "16533",
        "cont_pct_change_same_wk_last_year": "665.10%",
        "init_claims": "4190",
        "init_pct_change_same_wk_last_year": "1008.50%"
    },
    "146": {
        "index": "146",
        "year": "2020",
        "month": "October",
        "timeframe": "2020 October",
        "month_code": "10",
        "week": "43",
        "continued_claims": "15243",
        "cont_pct_change_same_wk_last_year": "617.30%",
        "init_claims": "3015",
        "init_pct_change_same_wk_last_year": "848.10%"
    },
    "147": {
        "index": "147",
        "year": "2020",
        "month": "October",
        "timeframe": "2020 October",
        "month_code": "10",
        "week": "44",
        "continued_claims": "14261",
        "cont_pct_change_same_wk_last_year": "576.20%",
        "init_claims": "2655",
        "init_pct_change_same_wk_last_year": "732.30%"
    },
    "148": {
        "index": "148",
        "year": "2020",
        "month": "November",
        "timeframe": "2020 November",
        "month_code": "11",
        "week": "45",
        "continued_claims": "13502",
        "cont_pct_change_same_wk_last_year": "538.70%",
        "init_claims": "2665",
        "init_pct_change_same_wk_last_year": "594.00%"
    },
    "149": {
        "index": "149",
        "year": "2020",
        "month": "November",
        "timeframe": "2020 November",
        "month_code": "11",
        "week": "46",
        "continued_claims": "12285",
        "cont_pct_change_same_wk_last_year": "471.90%",
        "init_claims": "2932",
        "init_pct_change_same_wk_last_year": "698.90%"
    },
    "150": {
        "index": "150",
        "year": "2020",
        "month": "November",
        "timeframe": "2020 November",
        "month_code": "11",
        "week": "47",
        "continued_claims": "10797",
        "cont_pct_change_same_wk_last_year": "420.80%",
        "init_claims": "3771",
        "init_pct_change_same_wk_last_year": "845.10%"
    },
    "151": {
        "index": "151",
        "year": "2020",
        "month": "November",
        "timeframe": "2020 November",
        "month_code": "11",
        "week": "48",
        "continued_claims": "10662",
        "cont_pct_change_same_wk_last_year": "396.40%",
        "init_claims": "3951",
        "init_pct_change_same_wk_last_year": "1519.30%"
    },
    "152": {
        "index": "152",
        "year": "2020",
        "month": "December",
        "timeframe": "2020 December",
        "month_code": "12",
        "week": "49",
        "continued_claims": "10521",
        "cont_pct_change_same_wk_last_year": "382.20%",
        "init_claims": "7213",
        "init_pct_change_same_wk_last_year": "1629.70%"
    },
    "153": {
        "index": "153",
        "year": "2020",
        "month": "December",
        "timeframe": "2020 December",
        "month_code": "12",
        "week": "50",
        "continued_claims": "10206",
        "cont_pct_change_same_wk_last_year": "325.40%",
        "init_claims": "4819",
        "init_pct_change_same_wk_last_year": "749.90%"
    },
    "154": {
        "index": "154",
        "year": "2020",
        "month": "December",
        "timeframe": "2020 December",
        "month_code": "12",
        "week": "51",
        "continued_claims": "9915",
        "cont_pct_change_same_wk_last_year": "296.40%",
        "init_claims": "3068",
        "init_pct_change_same_wk_last_year": "537.80%"
    },
    "155": {
        "index": "155",
        "year": "2020",
        "month": "December",
        "timeframe": "2020 December",
        "month_code": "12",
        "week": "52",
        "continued_claims": "10031",
        "cont_pct_change_same_wk_last_year": "267.00%",
        "init_claims": "2501",
        "init_pct_change_same_wk_last_year": "574.10%"
    },
    "156": {
        "index": "156",
        "year": "2021",
        "month": "January",
        "timeframe": "2021 January",
        "month_code": "1",
        "week": "1",
        "continued_claims": "13084",
        "cont_pct_change_same_wk_last_year": "360.90%",
        "init_claims": "2313",
        "init_pct_change_same_wk_last_year": "410.60%"
    },
    "157": {
        "index": "157",
        "year": "2021",
        "month": "January",
        "timeframe": "2021 January",
        "month_code": "1",
        "week": "2",
        "continued_claims": "13267",
        "cont_pct_change_same_wk_last_year": "360.70%",
        "init_claims": "15914",
        "init_pct_change_same_wk_last_year": "2592.70%"
    },
    "158": {
        "index": "158",
        "year": "2021",
        "month": "January",
        "timeframe": "2021 January",
        "month_code": "1",
        "week": "3",
        "continued_claims": "13084",
        "cont_pct_change_same_wk_last_year": "347.30%",
        "init_claims": "4063",
        "init_pct_change_same_wk_last_year": "768.20%"
    },
    "159": {
        "index": "159",
        "year": "2021",
        "month": "January",
        "timeframe": "2021 January",
        "month_code": "1",
        "week": "4",
        "continued_claims": "9896",
        "cont_pct_change_same_wk_last_year": "236.90%",
        "init_claims": "3653",
        "init_pct_change_same_wk_last_year": "769.80%"
    },
    "160": {
        "index": "160",
        "year": "2021",
        "month": "January",
        "timeframe": "2021 January",
        "month_code": "1",
        "week": "5",
        "continued_claims": "9159",
        "cont_pct_change_same_wk_last_year": "198.90%",
        "init_claims": "4371",
        "init_pct_change_same_wk_last_year": "950.70%"
    },
    "161": {
        "index": "161",
        "year": "2021",
        "month": "February",
        "timeframe": "2021 February",
        "month_code": "2",
        "week": "6",
        "continued_claims": "9168",
        "cont_pct_change_same_wk_last_year": "198.00%",
        "init_claims": "4451",
        "init_pct_change_same_wk_last_year": "985.60%"
    },
    "162": {
        "index": "162",
        "year": "2021",
        "month": "February",
        "timeframe": "2021 February",
        "month_code": "2",
        "week": "7",
        "continued_claims": "8852",
        "cont_pct_change_same_wk_last_year": "182.90%",
        "init_claims": "3560",
        "init_pct_change_same_wk_last_year": "831.90%"
    },
    "163": {
        "index": "163",
        "year": "2021",
        "month": "February",
        "timeframe": "2021 February",
        "month_code": "2",
        "week": "8",
        "continued_claims": "8793",
        "cont_pct_change_same_wk_last_year": "191.90%",
        "init_claims": "3193",
        "init_pct_change_same_wk_last_year": "817.50%"
    },
    "164": {
        "index": "164",
        "year": "2021",
        "month": "February",
        "timeframe": "2021 February",
        "month_code": "2",
        "week": "9",
        "continued_claims": "8553",
        "cont_pct_change_same_wk_last_year": "187.40%",
        "init_claims": "3893",
        "init_pct_change_same_wk_last_year": "1101.50%"
    },
    "165": {
        "index": "165",
        "year": "2021",
        "month": "March",
        "timeframe": "2021 March",
        "month_code": "3",
        "week": "10",
        "continued_claims": "8212",
        "cont_pct_change_same_wk_last_year": "179.80%",
        "init_claims": "4408",
        "init_pct_change_same_wk_last_year": "1379.20%"
    },
    "166": {
        "index": "166",
        "year": "2021",
        "month": "March",
        "timeframe": "2021 March",
        "month_code": "3",
        "week": "11",
        "continued_claims": "5295",
        "cont_pct_change_same_wk_last_year": "74.90%",
        "init_claims": "5579",
        "init_pct_change_same_wk_last_year": "1212.70%"
    },
    "167": {
        "index": "167",
        "year": "2021",
        "month": "March",
        "timeframe": "2021 March",
        "month_code": "3",
        "week": "12",
        "continued_claims": "7734",
        "cont_pct_change_same_wk_last_year": "63.30%",
        "init_claims": "5055",
        "init_pct_change_same_wk_last_year": "-50.30%"
    },
    "168": {
        "index": "168",
        "year": "2021",
        "month": "March",
        "timeframe": "2021 March",
        "month_code": "3",
        "week": "13",
        "continued_claims": "7427",
        "cont_pct_change_same_wk_last_year": "-30.50%",
        "init_claims": "4484",
        "init_pct_change_same_wk_last_year": "-66.90%"
    },
    "169": {
        "index": "169",
        "year": "2021",
        "month": "April",
        "timeframe": "2021 April",
        "month_code": "4",
        "week": "14",
        "continued_claims": "7359",
        "cont_pct_change_same_wk_last_year": "-59.50%",
        "init_claims": "3613",
        "init_pct_change_same_wk_last_year": "-73.40%"
    },
    "170": {
        "index": "170",
        "year": "2021",
        "month": "April",
        "timeframe": "2021 April",
        "month_code": "4",
        "week": "15",
        "continued_claims": "7448",
        "cont_pct_change_same_wk_last_year": "-69.70%",
        "init_claims": "21924",
        "init_pct_change_same_wk_last_year": "43.40%"
    },
    "171": {
        "index": "171",
        "year": "2021",
        "month": "April",
        "timeframe": "2021 April",
        "month_code": "4",
        "week": "16",
        "continued_claims": "7618",
        "cont_pct_change_same_wk_last_year": "-75.00%",
        "init_claims": "15718",
        "init_pct_change_same_wk_last_year": "49.60%"
    },
    "172": {
        "index": "172",
        "year": "2021",
        "month": "April",
        "timeframe": "2021 April",
        "month_code": "4",
        "week": "17",
        "continued_claims": "7663",
        "cont_pct_change_same_wk_last_year": "-76.80%",
        "init_claims": "4934",
        "init_pct_change_same_wk_last_year": "-41.90%"
    },
    "173": {
        "index": "173",
        "year": "2021",
        "month": "May",
        "timeframe": "2021 May",
        "month_code": "5",
        "week": "18",
        "continued_claims": "7766",
        "cont_pct_change_same_wk_last_year": "-77.70%",
        "init_claims": "2899",
        "init_pct_change_same_wk_last_year": "-61.80%"
    },
    "174": {
        "index": "174",
        "year": "2021",
        "month": "May",
        "timeframe": "2021 May",
        "month_code": "5",
        "week": "19",
        "continued_claims": "4990",
        "cont_pct_change_same_wk_last_year": "-86.00%",
        "init_claims": "2519",
        "init_pct_change_same_wk_last_year": "-53.20%"
    },
    "175": {
        "index": "175",
        "year": "2021",
        "month": "May",
        "timeframe": "2021 May",
        "month_code": "5",
        "week": "20",
        "continued_claims": "7501",
        "cont_pct_change_same_wk_last_year": "-79.20%",
        "init_claims": "1932",
        "init_pct_change_same_wk_last_year": "-66.90%"
    },
    "176": {
        "index": "176",
        "year": "2021",
        "month": "May",
        "timeframe": "2021 May",
        "month_code": "5",
        "week": "21",
        "continued_claims": "7178",
        "cont_pct_change_same_wk_last_year": "-79.90%",
        "init_claims": "1726",
        "init_pct_change_same_wk_last_year": "-67.10%"
    },
    "177": {
        "index": "177",
        "year": "2021",
        "month": "May",
        "timeframe": "2021 May",
        "month_code": "5",
        "week": "22",
        "continued_claims": "7208",
        "cont_pct_change_same_wk_last_year": "-79.60%",
        "init_claims": "1476",
        "init_pct_change_same_wk_last_year": "-67.70%"
    },
    "178": {
        "index": "178",
        "year": "2021",
        "month": "June",
        "timeframe": "2021 June",
        "month_code": "6",
        "week": "23",
        "continued_claims": "6871",
        "cont_pct_change_same_wk_last_year": "-80.60%",
        "init_claims": "1270",
        "init_pct_change_same_wk_last_year": "-72.70%"
    },
    "179": {
        "index": "179",
        "year": "2021",
        "month": "June",
        "timeframe": "2021 June",
        "month_code": "6",
        "week": "24",
        "continued_claims": "6472",
        "cont_pct_change_same_wk_last_year": "-81.70%",
        "init_claims": "1311",
        "init_pct_change_same_wk_last_year": "-75.30%"
    },
    "180": {
        "index": "180",
        "year": "2021",
        "month": "June",
        "timeframe": "2021 June",
        "month_code": "6",
        "week": "25",
        "continued_claims": "6028",
        "cont_pct_change_same_wk_last_year": "-82.70%",
        "init_claims": "1410",
        "init_pct_change_same_wk_last_year": "-78.30%"
    },
    "181": {
        "index": "181",
        "year": "2021",
        "month": "June",
        "timeframe": "2021 June",
        "month_code": "6",
        "week": "26",
        "continued_claims": "8453",
        "cont_pct_change_same_wk_last_year": "-75.80%",
        "init_claims": "1451",
        "init_pct_change_same_wk_last_year": "-86.90%"
    }
}